test_gpu.py
hf-test/tpu_benchmark.py
packages/test_gpu.py
hf_test-0.0.0.dist-info/METADATA
hf_test-0.0.0.dist-info/WHEEL
hf_test-0.0.0.dist-info/top_level.txt
hf_test-0.0.0.dist-info/RECORD
